odoo/addons/account_payment_term_restriction/README.rst
odoo/addons/account_payment_term_restriction/__init__.py
odoo/addons/account_payment_term_restriction/__manifest__.py
odoo/addons/account_payment_term_restriction/i18n/account_payment_term_restriction.pot
odoo/addons/account_payment_term_restriction/i18n/it.po
odoo/addons/account_payment_term_restriction/models/__init__.py
odoo/addons/account_payment_term_restriction/models/account_move.py
odoo/addons/account_payment_term_restriction/models/account_payment_term.py
odoo/addons/account_payment_term_restriction/readme/CONFIGURE.rst
odoo/addons/account_payment_term_restriction/readme/CONTRIBUTORS.rst
odoo/addons/account_payment_term_restriction/readme/DESCRIPTION.rst
odoo/addons/account_payment_term_restriction/static/description/icon.png
odoo/addons/account_payment_term_restriction/static/description/index.html
odoo/addons/account_payment_term_restriction/tests/__init__.py
odoo/addons/account_payment_term_restriction/tests/test_account_payment_term_restriction.py
odoo/addons/account_payment_term_restriction/views/account_payment_term.xml
odoo_addon_account_payment_term_restriction-16.0.1.0.0.4.dist-info/METADATA
odoo_addon_account_payment_term_restriction-16.0.1.0.0.4.dist-info/WHEEL
odoo_addon_account_payment_term_restriction-16.0.1.0.0.4.dist-info/top_level.txt
odoo_addon_account_payment_term_restriction-16.0.1.0.0.4.dist-info/RECORD
