Metadata-Version: 2.1
Name: odoo-addon-account_payment_term_restriction
Version: 16.0.1.0.0.4
Summary: Restricts the usage of Payment Terms Journal Entries
Home-page: https://github.com/OCA/account-payment
Author: ForgeFlow, Odoo Community Association (OCA)
Author-email: support@odoo-community.org
License: LGPL-3
Classifier: Programming Language :: Python
Classifier: Framework :: Odoo
Classifier: Framework :: Odoo :: 16.0
Classifier: License :: OSI Approved :: GNU Lesser General Public License v3 (LGPLv3)
Requires-Python: >=3.10
Requires-Dist: odoo<16.1dev,>=16.0a
